ga_solver/__init__.py
ga_solver/ga_solver.py
ga_solver/pop_selectors.py
ga_solver/range_dict.py
ga_solver-0.1.2.dist-info/WHEEL
ga_solver-0.1.2.dist-info/METADATA
ga_solver-0.1.2.dist-info/RECORD
