Metadata-Version: 2.1
Name: ga-solver
Version: 0.1.2
Summary: A simple, pure-python Genetic Algorithm solver
License: MIT
Author: Felipe 'Bidu' Rodrigues
Author-email: felipe@felipevr.com
Requires-Python: >=3.7,<4.0
Classifier: License :: OSI Approved :: MIT License
Classifier: Programming Language :: Python :: 3
Classifier: Programming Language :: Python :: 3.7
